{
    "application": {
        "name": "SuperSID Pro",
        "version": "1.0.0",
        "debug": false,
        "first_run": false,
        "log_level": "INFO",
        "last_updated": "2025-12-11T14:40:26.473506"
    },
    "observatory": {
        "name": " Alejandor",
        "monitor_id": "281",
        "location": "Montevideo, Uruguay",
        "coordinates": {
            "latitude": -34.569,
            "longitude": -56.871,
            "elevation": 30
        },
        "timezone": "UTC",
        "contact": {
            "name": "Alejandro",
            "email": "aarevalo1234@hotmail.com"
        }
    },
    "vlf_stations": {
        "monitored_stations": [
            "VTX1",
            "JXN",
            "VTX2",
            "SAQ",
            "RDL",
            "VTX3",
            "VTX4",
            "GBZ",
            "NWC",
            "NPM",
            "GQD",
            "DHO38",
            "NAA",
            "NLK",
            "NML"
        ],
        "station_frequencies": {
            "VTX1": {
                "freq": 16.3,
                "location": "South Vijayanarayanam, India",
                "lat": 8.387015,
                "lon": 77.752762,
                "region": "asia",
                "type": "vlf"
            },
            "JXN": {
                "freq": 16.4,
                "location": "Novik, Norway",
                "lat": 66.974353,
                "lon": 13.873617,
                "region": "europe",
                "type": "vlf"
            },
            "VTX2": {
                "freq": 17,
                "location": "South Vijayanarayanam, India",
                "lat": 8.387015,
                "lon": 77.752762,
                "region": "asia",
                "type": "vlf"
            },
            "SAQ": {
                "freq": 17.2,
                "location": "Grimeton, Sweden",
                "lat": 57.113171,
                "lon": 12.397277,
                "region": "europe",
                "type": "vlf"
            },
            "RDL": {
                "freq": 18.1,
                "location": "Unknown Location",
                "lat": 0,
                "lon": 0,
                "region": "unknown",
                "type": "vlf"
            },
            "VTX3": {
                "freq": 18.2,
                "location": "South Vijayanarayanam, India",
                "lat": 8.387015,
                "lon": 77.752762,
                "region": "asia",
                "type": "vlf"
            },
            "VTX4": {
                "freq": 19.2,
                "location": "South Vijayanarayanam, India",
                "lat": 8.387015,
                "lon": 77.752762,
                "region": "asia",
                "type": "vlf"
            },
            "GBZ": {
                "freq": 19.58,
                "location": "Anthorn, UK",
                "lat": 54.911643,
                "lon": -3.278456,
                "region": "europe",
                "type": "vlf"
            },
            "NWC": {
                "freq": 19.8,
                "location": "North West Cape, Australia",
                "lat": -21.816328,
                "lon": 114.165586,
                "region": "asia",
                "type": "vlf"
            },
            "NPM": {
                "freq": 21.4,
                "location": "Lualualei, Hawaii, USA",
                "lat": 21.420166,
                "lon": -158.15114,
                "region": "americas",
                "type": "vlf"
            },
            "GQD": {
                "freq": 22.1,
                "location": "Skelton, UK",
                "lat": 54.731799,
                "lon": -2.883033,
                "region": "europe",
                "type": "vlf"
            },
            "DHO38": {
                "freq": 23.4,
                "location": "Rhauderfehn, Germany",
                "lat": 53.0789,
                "lon": 7.615,
                "region": "europe",
                "type": "vlf"
            },
            "NAA": {
                "freq": 24,
                "location": "Cutler, Maine, USA",
                "lat": 44.644936,
                "lon": -67.281639,
                "region": "americas",
                "type": "vlf"
            },
            "NLK": {
                "freq": 24.8,
                "location": "Jim Creek, Washington, USA",
                "lat": 48.203487,
                "lon": -121.916827,
                "region": "americas",
                "type": "vlf"
            },
            "NML": {
                "freq": 25.2,
                "location": "La Moure, North Dakota, USA",
                "lat": 46.36599,
                "lon": -98.335638,
                "region": "americas",
                "type": "vlf"
            }
        }
    },
    "monitoring": {
        "auto_start": true,
        "data_retention_days": 30,
        "export_format": "csv",
        "screenshot_interval": 300
    },
    "reporting": {
        "ftp_upload": false,
        "ftp_server": "sid-ftp.stanford.edu",
        "ftp_directory": "/incoming/SuperSID/NEW/",
        "local_tmp": "/tmp",
        "report_interval": 86400
    },
    "space_weather": {
        "enable_spaceweatherlive": true,
        "enable_swpc_noaa": true,
        "update_interval": 600
    },
    "vlf_system": {
        "audio_sample_rate": 11025,
        "audio_buffer_size": 1024,
        "audio_device": null,
        "storage_batch_size": 10,
        "anomaly_detection": true,
        "baseline_update_interval": 300
    },
    "data_sources": {
        "audio": {
            "enabled": true,
            "sample_rate": 11025,
            "buffer_size": 1024
        },
        "simulation": {
            "enabled": true,
            "frequencies": [
                24.0,
                19.8,
                23.4,
                19.6
            ],
            "amplitude_range": [
                0.001,
                0.01
            ]
        }
    }
}